README.rst
setup.py
AsyncVk/__init__.py
AsyncVk/api.py
AsyncVk/mixins.py
AsyncVk/utils.py
AsyncVk.egg-info/PKG-INFO
AsyncVk.egg-info/SOURCES.txt
AsyncVk.egg-info/dependency_links.txt
AsyncVk.egg-info/requires.txt
AsyncVk.egg-info/top_level.txt