Metadata-Version: 1.1
Name: AsyncVk
Version: 1.0-alpha
Summary: vk.com API async Python wrapper. Only Python 3.4+
Home-page: https://github.com/tsyganov-ivan/AsyncVk
Author: Ivan Tsyganov
Author-email: tsyganov.ivan@gmail.com
License: MIT License
Keywords: vk.com asyncio async api vk vkontakte wrappper
Platform: UNKNOWN
Classifier: Environment :: Web Environment
Classifier: Intended Audience :: Developers
Classifier: License :: OSI Approved :: MIT License
Classifier: Programming Language :: Python :: 3.4
Classifier: Topic :: Software Development :: Libraries :: Python Modules
